{
  "objectIdFieldName": "OBJECTID",
  "uniqueIdField": {
    "name": "OBJECTID",
    "isSystemMaintained": true
  },
  "globalIdFieldName": "",
  "geometryType": "esriGeometryPoint",
  "spatialReference": {
    "wkid": 4326,
    "latestWkid": 4326
  },
  "fields": [
    {
      "name": "OBJECTID",
      "type": "esriFieldTypeOID",
      "alias": "OBJECTID",
      "sqlType": "sqlTypeOther",
      "domain": null,
      "defaultValue": null
    },
    {
      "name": "IncidentName",
      "type": "esriFieldTypeString",
      "alias": "Incident Name",
      "sqlType": "sqlTypeOther",
      "length": 50,
      "domain": null,
      "defaultValue": null
    },
    {
      "name": "IncidentTypeCategory",
      "type": "esriFieldTypeString",
      "alias": "Incident Type Category",
      "sqlType": "sqlTypeOther",
      "length": 50,
      "domain": null,
      "defaultValue": null
    },
    {
      "name": "UniqueFireIdentifier",
      "type": "esriFieldTypeString",
      "alias": "Unique Fire Identifier",
      "sqlType": "sqlTypeOther",
      "length": 22,
      "domain": null,
      "defaultValue": null
    },
    {
      "name": "DailyAcres",
      "type": "esriFieldTypeDouble",
      "alias": "Daily Acres",
      "sqlType": "sqlTypeOther",
      "domain": null,
      "defaultValue": null
    },
    {
      "name": "CalculatedAcres",
      "type": "esriFieldTypeDouble",
      "alias": "Calculated Acres",
      "sqlType": "sqlTypeOther",
      "domain": null,
      "defaultValue": null
    },
    {
      "name": "PercentContained",
      "type": "esriFieldTypeDouble",
      "alias": "Percent Contained",
      "sqlType": "sqlTypeOther",
      "domain": null,
      "defaultValue": null
    },
    {
      "name": "ICS209ReportDateTime",
      "type": "esriFieldTypeDate",
      "alias": "ICS209 Report Date Time",
      "sqlType": "sqlTypeOther",
      "length": 8,
      "domain": null,
      "defaultValue": null
    },
    {
      "name": "FireDiscoveryDateTime",
      "type": "esriFieldTypeDate",
      "alias": "Fire Discovery Date Time",
      "sqlType": "sqlTypeOther",
      "length": 8,
      "domain": null,
      "defaultValue": null
    },
    {
      "name": "DiscoveryAcres",
      "type": "esriFieldTypeDouble",
      "alias": "Discovery Acres",
      "sqlType": "sqlTypeOther",
      "domain": null,
      "defaultValue": null
    },
    {
      "name": "POOCounty",
      "type": "esriFieldTypeString",
      "alias": "Point of Orgin County",
      "sqlType": "sqlTypeOther",
      "length": 100,
      "domain": null,
      "defaultValue": null
    },
    {
      "name": "POOState",
      "type": "esriFieldTypeString",
      "alias": "Point of Orgin State",
      "sqlType": "sqlTypeOther",
      "length": 6,
      "domain": null,
      "defaultValue": null
    },
    {
      "name": "FireCause",
      "type": "esriFieldTypeString",
      "alias": "Cause",
      "sqlType": "sqlTypeOther",
      "length": 15,
      "domain": null,
      "defaultValue": null
    },
    {
      "name": "FireCauseGeneral",
      "type": "esriFieldTypeString",
      "alias": "Cause General",
      "sqlType": "sqlTypeOther",
      "length": 100,
      "domain": null,
      "defaultValue": null
    },
    {
      "name": "GACC",
      "type": "esriFieldTypeString",
      "alias": "Geographic Area Coordination Center",
      "sqlType": "sqlTypeOther",
      "length": 50,
      "domain": null,
      "defaultValue": null
    },
    {
      "name": "TotalIncidentPersonnel",
      "type": "esriFieldTypeSmallInteger",
      "alias": "Total Incident Personnel",
      "sqlType": "sqlTypeOther",
      "domain": null,
      "defaultValue": null
    },
    {
      "name": "IncidentManagementOrganization",
      "type": "esriFieldTypeString",
      "alias": "Incident Mgmt Organization",
      "sqlType": "sqlTypeOther",
      "length": 255,
      "domain": null,
      "defaultValue": null
    },
    {
      "name": "FireMgmtComplexity",
      "type": "esriFieldTypeString",
      "alias": "Mgmt Complexity",
      "sqlType": "sqlTypeOther",
      "length": 25,
      "domain": null,
      "defaultValue": null
    },
    {
      "name": "ResidencesDestroyed",
      "type": "esriFieldTypeInteger",
      "alias": "Residences Destroyed",
      "sqlType": "sqlTypeOther",
      "domain": null,
      "defaultValue": null
    },
    {
      "name": "OtherStructuresDestroyed",
      "type": "esriFieldTypeInteger",
      "alias": "Other Structures Destroyed",
      "sqlType": "sqlTypeOther",
      "domain": null,
      "defaultValue": null
    },
    {
      "name": "Injuries",
      "type": "esriFieldTypeSmallInteger",
      "alias": "Injuries",
      "sqlType": "sqlTypeOther",
      "domain": null,
      "defaultValue": null
    },
    {
      "name": "Fatalities",
      "type": "esriFieldTypeSmallInteger",
      "alias": "Fatalities",
      "sqlType": "sqlTypeOther",
      "domain": null,
      "defaultValue": null
    },
    {
      "name": "PredominantFuelGroup",
      "type": "esriFieldTypeString",
      "alias": "Predominant Fuel Group",
      "sqlType": "sqlTypeOther",
      "length": 100,
      "domain": null,
      "defaultValue": null
    },
    {
      "name": "PredominantFuelModel",
      "type": "esriFieldTypeString",
      "alias": "Predominant Fuel Model",
      "sqlType": "sqlTypeOther",
      "length": 50,
      "domain": null,
      "defaultValue": null
    },
    {
      "name": "PrimaryFuelModel",
      "type": "esriFieldTypeString",
      "alias": "Primary Fuel Model",
      "sqlType": "sqlTypeOther",
      "length": 30,
      "domain": null,
      "defaultValue": null
    },
    {
      "name": "ContainmentDateTime",
      "type": "esriFieldTypeDate",
      "alias": "Containment Date Time",
      "sqlType": "sqlTypeOther",
      "length": 8,
      "domain": null,
      "defaultValue": null
    },
    {
      "name": "ControlDateTime",
      "type": "esriFieldTypeDate",
      "alias": "Control Date Time",
      "sqlType": "sqlTypeOther",
      "length": 8,
      "domain": null,
      "defaultValue": null
    },
    {
      "name": "FinalAcres",
      "type": "esriFieldTypeDouble",
      "alias": "Final Acres",
      "sqlType": "sqlTypeOther",
      "domain": null,
      "defaultValue": null
    },
    {
      "name": "IsValid",
      "type": "esriFieldTypeInteger",
      "alias": "Is Valid",
      "sqlType": "sqlTypeOther",
      "domain": null,
      "defaultValue": null
    },
    {
      "name": "FireOutDateTime",
      "type": "esriFieldTypeDate",
      "alias": "Fire Out Date Time",
      "sqlType": "sqlTypeOther",
      "length": 8,
      "domain": null,
      "defaultValue": null
    },
    {
      "name": "ModifiedOnDateTime",
      "type": "esriFieldTypeDate",
      "alias": "Modified On Date Time",
      "sqlType": "sqlTypeOther",
      "length": 8,
      "domain": null,
      "defaultValue": null
    },
    {
      "name": "IncidentTypeKind",
      "type": "esriFieldTypeString",
      "alias": "Incident Type Kind",
      "sqlType": "sqlTypeOther",
      "length": 2,
      "domain": null,
      "defaultValue": null
    },
    {
      "name": "IrwinID",
      "type": "esriFieldTypeString",
      "alias": "IRWIN ID",
      "sqlType": "sqlTypeOther",
      "length": 40,
      "domain": null,
      "defaultValue": null
    },
    {
      "name": "GlobalID",
      "type": "esriFieldTypeString",
      "alias": "Global ID",
      "sqlType": "sqlTypeOther",
      "length": 40,
      "domain": null,
      "defaultValue": null
    },
    {
      "name": "ModifiedOnAge",
      "type": "esriFieldTypeSmallInteger",
      "alias": "Days Since Modified On Date",
      "sqlType": "sqlTypeOther",
      "domain": null,
      "defaultValue": null
    },
    {
      "name": "FireDiscoveryAge",
      "type": "esriFieldTypeSmallInteger",
      "alias": "Days Since Fire Discovery Date",
      "sqlType": "sqlTypeOther",
      "domain": null,
      "defaultValue": null
    }
  ],
  "features": [
    {
      "attributes": {
        "OBJECTID": 389,
        "IncidentName": "BO",
        "IncidentTypeCategory": "WF",
        "UniqueFireIdentifier": "2024-MTLG03-240309",
        "DailyAcres": 350,
        "CalculatedAcres": null,
        "PercentContained": null,
        "ICS209ReportDateTime": null,
        "FireDiscoveryDateTime": 1719687180000,
        "DiscoveryAcres": 45,
        "POOCounty": "Yellowstone",
        "POOState": "US-MT",
        "FireCause": "Undetermined",
        "FireCauseGeneral": null,
        "GACC": "NRCC",
        "TotalIncidentPersonnel": null,
        "IncidentManagementOrganization": null,
        "FireMgmtComplexity": null,
        "ResidencesDestroyed": null,
        "OtherStructuresDestroyed": null,
        "Injuries": null,
        "Fatalities": null,
        "PredominantFuelGroup": null,
        "PredominantFuelModel": null,
        "PrimaryFuelModel": null,
        "ContainmentDateTime": null,
        "ControlDateTime": null,
        "FinalAcres": null,
        "IsValid": 1,
        "FireOutDateTime": null,
        "ModifiedOnDateTime": 1719755216000,
        "IncidentTypeKind": "FI",
        "IrwinID": "ac78fb99-88ad-40cb-b52a-c788581b4dca",
        "GlobalID": "b2ed61c1-0258-4ad2-bd7b-8c8d22a18b9b",
        "ModifiedOnAge": 0,
        "FireDiscoveryAge": 0
      },
      "geometry": {
        "x": -108.56804999999997,
        "y": 45.84310000000005
      }
    },
    {
      "attributes": {
        "OBJECTID": 169,
        "IncidentName": "Tatanka",
        "IncidentTypeCategory": "WF",
        "UniqueFireIdentifier": "2024-MTCMR-000098",
        "DailyAcres": 185,
        "CalculatedAcres": null,
        "PercentContained": 20,
        "ICS209ReportDateTime": 1719610114000,
        "FireDiscoveryDateTime": 1719245520000,
        "DiscoveryAcres": 15,
        "POOCounty": "Phillips",
        "POOState": "US-MT",
        "FireCause": "Natural",
        "FireCauseGeneral": null,
        "GACC": "NRCC",
        "TotalIncidentPersonnel": 2,
        "IncidentManagementOrganization": "Type 4 IC",
        "FireMgmtComplexity": null,
        "ResidencesDestroyed": null,
        "OtherStructuresDestroyed": null,
        "Injuries": null,
        "Fatalities": null,
        "PredominantFuelGroup": null,
        "PredominantFuelModel": null,
        "PrimaryFuelModel": "Timber (Litter and Understory)",
        "ContainmentDateTime": null,
        "ControlDateTime": null,
        "FinalAcres": null,
        "IsValid": 1,
        "FireOutDateTime": null,
        "ModifiedOnDateTime": 1719760546000,
        "IncidentTypeKind": "FI",
        "IrwinID": "586fea6b-c547-4d12-9192-0fcff5ae9400",
        "GlobalID": "e10073d8-cda0-408b-94a0-2b80ed74258f",
        "ModifiedOnAge": 0,
        "FireDiscoveryAge": 6
      },
      "geometry": {
        "x": -107.72844999999995,
        "y": 47.62290000000007
      }
    },
    {
      "attributes": {
        "OBJECTID": 176,
        "IncidentName": "Running Wolf",
        "IncidentTypeCategory": "WF",
        "UniqueFireIdentifier": "2024-MTHLF-005065",
        "DailyAcres": 93,
        "CalculatedAcres": 79.132,
        "PercentContained": null,
        "ICS209ReportDateTime": null,
        "FireDiscoveryDateTime": 1719261926000,
        "DiscoveryAcres": 0.1,
        "POOCounty": "Judith Basin",
        "POOState": "US-MT",
        "FireCause": "Natural",
        "FireCauseGeneral": null,
        "GACC": "NRCC",
        "TotalIncidentPersonnel": null,
        "IncidentManagementOrganization": null,
        "FireMgmtComplexity": null,
        "ResidencesDestroyed": null,
        "OtherStructuresDestroyed": null,
        "Injuries": null,
        "Fatalities": null,
        "PredominantFuelGroup": null,
        "PredominantFuelModel": null,
        "PrimaryFuelModel": null,
        "ContainmentDateTime": null,
        "ControlDateTime": null,
        "FinalAcres": null,
        "IsValid": 1,
        "FireOutDateTime": null,
        "ModifiedOnDateTime": 1719620779000,
        "IncidentTypeKind": "FI",
        "IrwinID": "4727a447-4fe8-4d47-8b09-793072dadfcc",
        "GlobalID": "a87e0a4b-2817-4d06-b161-1f802881b2bc",
        "ModifiedOnAge": 1,
        "FireDiscoveryAge": 5
      },
      "geometry": {
        "x": -110.41299999999995,
        "y": 46.99466700000005
      }
    },
    {
      "attributes": {
        "OBJECTID": 196,
        "IncidentName": "East Charlie - Richland",
        "IncidentTypeCategory": "WF",
        "UniqueFireIdentifier": "2024-MTLG27-000171",
        "DailyAcres": 76.5,
        "CalculatedAcres": null,
        "PercentContained": null,
        "ICS209ReportDateTime": null,
        "FireDiscoveryDateTime": 1711979340000,
        "DiscoveryAcres": 76.5,
        "POOCounty": "Richland",
        "POOState": "US-MT",
        "FireCause": "Human",
        "FireCauseGeneral": null,
        "GACC": "NRCC",
        "TotalIncidentPersonnel": null,
        "IncidentManagementOrganization": null,
        "FireMgmtComplexity": null,
        "ResidencesDestroyed": null,
        "OtherStructuresDestroyed": null,
        "Injuries": null,
        "Fatalities": null,
        "PredominantFuelGroup": null,
        "PredominantFuelModel": null,
        "PrimaryFuelModel": null,
        "ContainmentDateTime": null,
        "ControlDateTime": null,
        "FinalAcres": null,
        "IsValid": 1,
        "FireOutDateTime": null,
        "ModifiedOnDateTime": 1719323634000,
        "IncidentTypeKind": "FI",
        "IrwinID": "1e8f24d9-bb1e-4497-a75c-6a07d8c8d3d5",
        "GlobalID": "eb18244a-f685-4a24-a45b-b46f1af36d64",
        "ModifiedOnAge": 5,
        "FireDiscoveryAge": 90
      },
      "geometry": {
        "x": -104.67700499999995,
        "y": 47.867102000000045
      }
    },
    {
      "attributes": {
        "OBJECTID": 274,
        "IncidentName": "Ridgetop",
        "IncidentTypeCategory": "WF",
        "UniqueFireIdentifier": "2024-MTCRA-240295",
        "DailyAcres": 73,
        "CalculatedAcres": null,
        "PercentContained": null,
        "ICS209ReportDateTime": null,
        "FireDiscoveryDateTime": 1719518940000,
        "DiscoveryAcres": 15,
        "POOCounty": "Big Horn",
        "POOState": "US-MT",
        "FireCause": "Undetermined",
        "FireCauseGeneral": null,
        "GACC": "NRCC",
        "TotalIncidentPersonnel": null,
        "IncidentManagementOrganization": null,
        "FireMgmtComplexity": null,
        "ResidencesDestroyed": null,
        "OtherStructuresDestroyed": null,
        "Injuries": null,
        "Fatalities": null,
        "PredominantFuelGroup": null,
        "PredominantFuelModel": null,
        "PrimaryFuelModel": null,
        "ContainmentDateTime": null,
        "ControlDateTime": null,
        "FinalAcres": null,
        "IsValid": 1,
        "FireOutDateTime": null,
        "ModifiedOnDateTime": 1719582765000,
        "IncidentTypeKind": "FI",
        "IrwinID": "1748280e-8ddd-45c0-b689-a23573b3354e",
        "GlobalID": "c889349a-20f9-4702-9b43-3dc43667a9f7",
        "ModifiedOnAge": 2,
        "FireDiscoveryAge": 2
      },
      "geometry": {
        "x": -107.69484999999997,
        "y": 45.63793500000003
      }
    },
    {
      "attributes": {
        "OBJECTID": 212,
        "IncidentName": "Shelter Belt - Fallon",
        "IncidentTypeCategory": "WF",
        "UniqueFireIdentifier": "2024-MTLG39-000178",
        "DailyAcres": 67.2,
        "CalculatedAcres": null,
        "PercentContained": null,
        "ICS209ReportDateTime": null,
        "FireDiscoveryDateTime": 1719349020000,
        "DiscoveryAcres": 20,
        "POOCounty": "Fallon",
        "POOState": "US-MT",
        "FireCause": "Human",
        "FireCauseGeneral": null,
        "GACC": "NRCC",
        "TotalIncidentPersonnel": null,
        "IncidentManagementOrganization": null,
        "FireMgmtComplexity": null,
        "ResidencesDestroyed": null,
        "OtherStructuresDestroyed": null,
        "Injuries": null,
        "Fatalities": null,
        "PredominantFuelGroup": null,
        "PredominantFuelModel": null,
        "PrimaryFuelModel": null,
        "ContainmentDateTime": null,
        "ControlDateTime": null,
        "FinalAcres": null,
        "IsValid": 1,
        "FireOutDateTime": null,
        "ModifiedOnDateTime": 1719412487000,
        "IncidentTypeKind": "FI",
        "IrwinID": "caea7a64-92ca-4b0c-a6ca-6f51651a3a8c",
        "GlobalID": "3355a921-f54e-4420-8fad-5a3ee0fea21a",
        "ModifiedOnAge": 4,
        "FireDiscoveryAge": 4
      },
      "geometry": {
        "x": -104.33876999999995,
        "y": 46.083470000000034
      }
    },
    {
      "attributes": {
        "OBJECTID": 6,
        "IncidentName": "GORE HILL 315",
        "IncidentTypeCategory": "WF",
        "UniqueFireIdentifier": "2024-MTLG02-005021",
        "DailyAcres": 40,
        "CalculatedAcres": null,
        "PercentContained": null,
        "ICS209ReportDateTime": null,
        "FireDiscoveryDateTime": 1710537482000,
        "DiscoveryAcres": 1,
        "POOCounty": "Cascade",
        "POOState": "US-MT",
        "FireCause": "Undetermined",
        "FireCauseGeneral": null,
        "GACC": "NRCC",
        "TotalIncidentPersonnel": null,
        "IncidentManagementOrganization": null,
        "FireMgmtComplexity": null,
        "ResidencesDestroyed": null,
        "OtherStructuresDestroyed": null,
        "Injuries": null,
        "Fatalities": null,
        "PredominantFuelGroup": null,
        "PredominantFuelModel": null,
        "PrimaryFuelModel": null,
        "ContainmentDateTime": null,
        "ControlDateTime": null,
        "FinalAcres": null,
        "IsValid": 1,
        "FireOutDateTime": null,
        "ModifiedOnDateTime": 1719409387000,
        "IncidentTypeKind": "FI",
        "IrwinID": "349e1294-f26a-4f99-bed1-901c5e181858",
        "GlobalID": "b7f1061d-2c12-44e2-9684-88fb011f4d1b",
        "ModifiedOnAge": 4,
        "FireDiscoveryAge": 106
      },
      "geometry": {
        "x": -111.38236899999998,
        "y": 47.43439100000006
      }
    },
    {
      "attributes": {
        "OBJECTID": 7,
        "IncidentName": "Gore Hill 315",
        "IncidentTypeCategory": "WF",
        "UniqueFireIdentifier": "2024-MTHDC-000116",
        "DailyAcres": 40,
        "CalculatedAcres": null,
        "PercentContained": null,
        "ICS209ReportDateTime": null,
        "FireDiscoveryDateTime": 1710537624000,
        "DiscoveryAcres": 0.1,
        "POOCounty": "Cascade",
        "POOState": "US-MT",
        "FireCause": "Undetermined",
        "FireCauseGeneral": null,
        "GACC": "NRCC",
        "TotalIncidentPersonnel": null,
        "IncidentManagementOrganization": null,
        "FireMgmtComplexity": null,
        "ResidencesDestroyed": null,
        "OtherStructuresDestroyed": null,
        "Injuries": null,
        "Fatalities": null,
        "PredominantFuelGroup": null,
        "PredominantFuelModel": null,
        "PrimaryFuelModel": null,
        "ContainmentDateTime": null,
        "ControlDateTime": null,
        "FinalAcres": null,
        "IsValid": 1,
        "FireOutDateTime": null,
        "ModifiedOnDateTime": 1719329275000,
        "IncidentTypeKind": "FI",
        "IrwinID": "98808ef8-32e7-4578-ac89-4287d592c1c6",
        "GlobalID": "3fd9bfee-92f2-4e74-ba7d-706365f29c9b",
        "ModifiedOnAge": 5,
        "FireDiscoveryAge": 106
      },
      "geometry": {
        "x": -111.38236899999998,
        "y": 47.43439100000006
      }
    },
    {
      "attributes": {
        "OBJECTID": 165,
        "IncidentName": "Wood Gulch",
        "IncidentTypeCategory": "WF",
        "UniqueFireIdentifier": "2024-MTNCA-000170",
        "DailyAcres": 12,
        "CalculatedAcres": null,
        "PercentContained": null,
        "ICS209ReportDateTime": null,
        "FireDiscoveryDateTime": 1719170880000,
        "DiscoveryAcres": 5,
        "POOCounty": "Big Horn",
        "POOState": "US-MT",
        "FireCause": "Natural",
        "FireCauseGeneral": null,
        "GACC": "NRCC",
        "TotalIncidentPersonnel": null,
        "IncidentManagementOrganization": null,
        "FireMgmtComplexity": null,
        "ResidencesDestroyed": null,
        "OtherStructuresDestroyed": null,
        "Injuries": null,
        "Fatalities": null,
        "PredominantFuelGroup": null,
        "PredominantFuelModel": null,
        "PrimaryFuelModel": null,
        "ContainmentDateTime": null,
        "ControlDateTime": null,
        "FinalAcres": null,
        "IsValid": 1,
        "FireOutDateTime": null,
        "ModifiedOnDateTime": 1719239651000,
        "IncidentTypeKind": "FI",
        "IrwinID": "c92e85e5-93c7-4814-9a25-09dfc4903203",
        "GlobalID": "482f3553-3846-4c39-9e51-6d4086cf4a13",
        "ModifiedOnAge": 6,
        "FireDiscoveryAge": 6
      },
      "geometry": {
        "x": -106.89933299999996,
        "y": 45.62500000000006
      }
    },
    {
      "attributes": {
        "OBJECTID": 310,
        "IncidentName": "Corral Creek - Powder River",
        "IncidentTypeCategory": "WF",
        "UniqueFireIdentifier": "2024-MTLG09-000182",
        "DailyAcres": 0.25,
        "CalculatedAcres": null,
        "PercentContained": null,
        "ICS209ReportDateTime": null,
        "FireDiscoveryDateTime": 1719538200000,
        "DiscoveryAcres": 0.25,
        "POOCounty": "Powder River",
        "POOState": "US-MT",
        "FireCause": "Natural",
        "FireCauseGeneral": null,
        "GACC": "NRCC",
        "TotalIncidentPersonnel": null,
        "IncidentManagementOrganization": null,
        "FireMgmtComplexity": null,
        "ResidencesDestroyed": null,
        "OtherStructuresDestroyed": null,
        "Injuries": null,
        "Fatalities": null,
        "PredominantFuelGroup": null,
        "PredominantFuelModel": null,
        "PrimaryFuelModel": null,
        "ContainmentDateTime": null,
        "ControlDateTime": null,
        "FinalAcres": null,
        "IsValid": 1,
        "FireOutDateTime": null,
        "ModifiedOnDateTime": 1719586009000,
        "IncidentTypeKind": "FI",
        "IrwinID": "e4a9b0ee-971d-408e-93ae-3dab9cdda2ec",
        "GlobalID": "6da1542f-1f4b-4953-be6c-37267b731dda",
        "ModifiedOnAge": 2,
        "FireDiscoveryAge": 2
      },
      "geometry": {
        "x": -105.33194999999995,
        "y": 45.456990000000076
      }
    },
    {
      "attributes": {
        "OBJECTID": 336,
        "IncidentName": "MM 148 - Custer",
        "IncidentTypeCategory": "WF",
        "UniqueFireIdentifier": "2024-MTLG14-000184",
        "DailyAcres": 0.25,
        "CalculatedAcres": null,
        "PercentContained": null,
        "ICS209ReportDateTime": null,
        "FireDiscoveryDateTime": 1719605044000,
        "DiscoveryAcres": 0.25,
        "POOCounty": "Custer",
        "POOState": "US-MT",
        "FireCause": "Human",
        "FireCauseGeneral": null,
        "GACC": "NRCC",
        "TotalIncidentPersonnel": null,
        "IncidentManagementOrganization": null,
        "FireMgmtComplexity": null,
        "ResidencesDestroyed": null,
        "OtherStructuresDestroyed": null,
        "Injuries": null,
        "Fatalities": null,
        "PredominantFuelGroup": null,
        "PredominantFuelModel": null,
        "PrimaryFuelModel": null,
        "ContainmentDateTime": null,
        "ControlDateTime": null,
        "FinalAcres": null,
        "IsValid": 1,
        "FireOutDateTime": null,
        "ModifiedOnDateTime": 1719612589000,
        "IncidentTypeKind": "FI",
        "IrwinID": "ab7e8fba-4b2b-4c83-9639-95d9a26f8fdf",
        "GlobalID": "9b2e2772-45c5-4e99-b4d3-521a44bf84b9",
        "ModifiedOnAge": 1,
        "FireDiscoveryAge": 1
      },
      "geometry": {
        "x": -105.70901699999996,
        "y": 46.49973300000005
      }
    },
    {
      "attributes": {
        "OBJECTID": 206,
        "IncidentName": "Mondell",
        "IncidentTypeCategory": "WF",
        "UniqueFireIdentifier": "2024-MTLG22-240283",
        "DailyAcres": 0.1,
        "CalculatedAcres": null,
        "PercentContained": null,
        "ICS209ReportDateTime": null,
        "FireDiscoveryDateTime": 1719361861000,
        "DiscoveryAcres": 0.1,
        "POOCounty": "Big Horn",
        "POOState": "US-MT",
        "FireCause": "Undetermined",
        "FireCauseGeneral": null,
        "GACC": "NRCC",
        "TotalIncidentPersonnel": null,
        "IncidentManagementOrganization": null,
        "FireMgmtComplexity": null,
        "ResidencesDestroyed": null,
        "OtherStructuresDestroyed": null,
        "Injuries": null,
        "Fatalities": null,
        "PredominantFuelGroup": null,
        "PredominantFuelModel": null,
        "PrimaryFuelModel": null,
        "ContainmentDateTime": null,
        "ControlDateTime": null,
        "FinalAcres": null,
        "IsValid": 1,
        "FireOutDateTime": null,
        "ModifiedOnDateTime": 1719700997000,
        "IncidentTypeKind": "FI",
        "IrwinID": "c3b8aa48-d3db-4196-adc3-8221c5a75de2",
        "GlobalID": "3e5f75a7-778f-4389-8230-46d3e35b63fd",
        "ModifiedOnAge": 0,
        "FireDiscoveryAge": 4
      },
      "geometry": {
        "x": -107.39591699999994,
        "y": 45.129710000000046
      }
    },
    {
      "attributes": {
        "OBJECTID": 450,
        "IncidentName": "Massy - Custer",
        "IncidentTypeCategory": "WF",
        "UniqueFireIdentifier": "2024-MTLG14-000186",
        "DailyAcres": 0.1,
        "CalculatedAcres": null,
        "PercentContained": null,
        "ICS209ReportDateTime": null,
        "FireDiscoveryDateTime": 1719626400000,
        "DiscoveryAcres": 0.1,
        "POOCounty": "Custer",
        "POOState": "US-MT",
        "FireCause": "Human",
        "FireCauseGeneral": null,
        "GACC": "NRCC",
        "TotalIncidentPersonnel": null,
        "IncidentManagementOrganization": null,
        "FireMgmtComplexity": null,
        "ResidencesDestroyed": null,
        "OtherStructuresDestroyed": null,
        "Injuries": null,
        "Fatalities": null,
        "PredominantFuelGroup": null,
        "PredominantFuelModel": null,
        "PrimaryFuelModel": null,
        "ContainmentDateTime": null,
        "ControlDateTime": null,
        "FinalAcres": null,
        "IsValid": 1,
        "FireOutDateTime": null,
        "ModifiedOnDateTime": 1719763953000,
        "IncidentTypeKind": "FI",
        "IrwinID": "18de813a-eaea-472c-ae0d-3892b6f3c45f",
        "GlobalID": "609778f2-9460-4bed-83c8-174c6cb55ba2",
        "ModifiedOnAge": 0,
        "FireDiscoveryAge": 1
      },
      "geometry": {
        "x": -105.13588299999998,
        "y": 46.42270000000008
      }
    },
    {
      "attributes": {
        "OBJECTID": 451,
        "IncidentName": "Fireworks 1 - Custer",
        "IncidentTypeCategory": "WF",
        "UniqueFireIdentifier": "2024-MTLG14-000187",
        "DailyAcres": 0.1,
        "CalculatedAcres": null,
        "PercentContained": null,
        "ICS209ReportDateTime": null,
        "FireDiscoveryDateTime": 1719633600000,
        "DiscoveryAcres": 0.1,
        "POOCounty": "Custer",
        "POOState": "US-MT",
        "FireCause": "Human",
        "FireCauseGeneral": null,
        "GACC": "NRCC",
        "TotalIncidentPersonnel": null,
        "IncidentManagementOrganization": null,
        "FireMgmtComplexity": null,
        "ResidencesDestroyed": null,
        "OtherStructuresDestroyed": null,
        "Injuries": null,
        "Fatalities": null,
        "PredominantFuelGroup": null,
        "PredominantFuelModel": null,
        "PrimaryFuelModel": null,
        "ContainmentDateTime": null,
        "ControlDateTime": null,
        "FinalAcres": null,
        "IsValid": 1,
        "FireOutDateTime": null,
        "ModifiedOnDateTime": 1719764140000,
        "IncidentTypeKind": "FI",
        "IrwinID": "9c7660d0-a38c-4b78-8d87-44295bc35f25",
        "GlobalID": "190b915b-3dfe-4bfb-ace2-146cc444f464",
        "ModifiedOnAge": 0,
        "FireDiscoveryAge": 1
      },
      "geometry": {
        "x": -105.77611699999994,
        "y": 46.42870000000005
      }
    }
  ]
}
